{
"views1_delay25":[
  {"id":"Glow_01_16","type":"image","resPath":"effects/effectsRes/Glow_01.png",
     "ax":0.5,"ay":0.5,"x":-5,"y":80,"z":1,"scaleX":1.0,"scaleY":1.0,"blend":[770,1],"opacity":0,"color":[255,0,0],"action":[]},
 ],
"views1_delay49":[
  {"id":"lizi_00047png_1","type":"image","resPath":"effects/effectsRes/lizi_00047.png",
     "ax":0.5,"ay":0.5,"x":26,"y":41,"z":2,"scaleX":2.0,"scaleY":2.0,"blend":[1,771],"opacity":0,"color":[255,238,190],"action":[]},
  {"id":"lizi_00047png_1_0","type":"image","resPath":"effects/effectsRes/lizi_00047.png",
     "ax":0.5,"ay":0.5,"x":26,"y":41,"z":3,"scaleX":2.0,"scaleY":2.0,"blend":[770,1],"opacity":0,"color":[255,214,0],"action":[]},
 ],
"views1_delay49_move":[
  {"id":"xly_1","type":"image","resPath":"effects/effectsRes/xly.png",
     "ax":0.5,"ay":0.5,"x":47,"y":138,"z":-2,"scaleX":0.1,"scaleY":0.1,"blend":[1,771],"opacity":0,"action":[]},
  {"id":"Glow_01_2","type":"image","resPath":"effects/effectsRes/Glow_01.png",
     "ax":0.5,"ay":0.5,"x":47,"y":138,"z":2,"scaleX":0.25,"scaleY":0.25,"blend":[770,1],"color":[255,0,0],"action":[]},
  {"id":"Particle_3_0","type":"particle","resPath":"particles/battleEffectUchiha5.json",
     "x":-412,"y":317,"z":0,"scaleX":0.6,"scaleY":0.6,"blend":[1,771],"skewX":-53.7554,"skewY":-53.7549,"action":[]},
  {"id":"Particle_3","type":"particle","resPath":"particles/battleEffectUchiha2.json",
     "x":-412,"y":317,"z":3,"scaleX":1.0,"scaleY":1.0,"blend":[1,1],"skewX":-53.7554,"skewY":-53.7549,"action":[]},
  {"id":"Particle_3_0_0","type":"particle","resPath":"particles/battleEffectUchiha5.json",
     "x":-412,"y":317,"z":4,"scaleX":0.6,"scaleY":0.6,"blend":[770,1],"skewX":-53.7554,"skewY":-53.7549,"action":[]},
 ],
"views3_delay60":[
  {"id":"Glow_01_10","type":"image","resPath":"effects/effectsRes/Glow_01.png",
     "ax":0.5,"ay":0.5,"x":948,"y":-644,"z":-3,"scaleX":1.8,"scaleY":1.8,"blend":[770,1],"opacity":0,"color":[255,0,0],"action":[]},
  {"id":"Sharingan_00000_8","type":"image","resPath":"effects/effectsRes/xly.png",
     "ax":0.5,"ay":0.5,"x":948,"y":-644,"z":-2,"scaleX":0.15,"scaleY":0.15,"blend":[1,771],"opacity":0,"action":[]},
 ],
 "views3_delay64":[
  {"id":"Impact_00000_3_0","type":"animate","frames":4,"time":0.250,"name":"Impact_1_","tab":{"beginNum":0,"plist":"effects/effectsRes/Impact_1.plist","isRepeat":false},
     "ax":0.5,"ay":0.5,"x":948,"y":-597,"z":-5,"scaleX":1.0,"scaleY":1.0,"blend":[1,771],"opacity":0,"color":[255,0,0],"action":[]},
  {"id":"Impact_00000_3","type":"animate","frames":4,"time":0.250,"name":"Impact_1_","tab":{"beginNum":0,"plist":"effects/effectsRes/Impact_1.plist","isRepeat":false},
     "ax":0.5,"ay":0.5,"x":948,"y":-597,"z":-4,"scaleX":1.0,"scaleY":1.0,"blend":[770,1],"opacity":0,"action":[]},
 ],
"views3_delay65":[
  {"id":"Particle_1","type":"particle","resPath":"particles/battleEffectUchiha1.json",
     "x":490,"y":-281,"z":3,"scaleX":0.8,"scaleY":0.8,"blend":[1,1],"action":[]},
  {"id":"Sharingan_00000_9","type":"animate","frames":6,"time":0.833,"name":"Sharingan_","tab":{"beginNum":0,"plist":"effects/effectsRes/Sharingan.plist","isRepeat":true},
     "ax":0.5,"ay":0.22,"x":949,"y":-488,"z":-1,"scaleX":3.5,"scaleY":3.5,"blend":[1,771],"opacity":0,"action":[]},
  {"id":"Glow_01_10_0","type":"image","resPath":"effects/effectsRes/Glow_01.png",
     "ax":0.5,"ay":0.5,"x":948,"y":-647,"z":1,"scaleX":2.3,"scaleY":2.3,"blend":[770,1],"opacity":0,"color":[255,0,0],"action":[]},
  {"id":"Sharingan_00000_9_0","type":"animate","frames":6,"time":0.833,"name":"Sharingan_","tab":{"beginNum":0,"plist":"effects/effectsRes/Sharingan.plist","isRepeat":true},
     "ax":0.5,"ay":0.22,"x":949,"y":-488,"z":2,"scaleX":3.5,"scaleY":3.5,"blend":[1,1],"opacity":0,"action":[]},
 ],
 "views3_delay69":[
  {"id":"Particle_2","type":"particle","resPath":"particles/battleEffectUchiha4.json",
     "x":952,"y":-630,"z":-4,"scaleX":1.5,"scaleY":1.5,"blend":[1,1],"action":[]},
 ],
 "views4_delay19_Par":[
  {"id":"Flame_1_0","type":"particle","resPath":"particles/battleEffectUchiha3.json",
     "x":-172,"y":62,"z":1,"scaleX":1.0,"scaleY":1.0,"blend":[1,771],"skewX":90.0,"skewY":89.9703,"action":[]},
  {"id":"Flame_0_0_0","type":"particle","resPath":"particles/battleEffectUchiha3.json",
     "x":-158,"y":62,"z":2,"scaleX":1.0,"scaleY":1.0,"blend":[770,1],"skewX":90.0,"skewY":89.9773,"action":[]},
 ],
"views4_delay19":[
  {"id":"Glow_01_18_1_0","type":"image","resPath":"effects/effectsRes/Glow_01.png",
     "ax":0.5,"ay":0.5,"x":-173,"y":58,"z":3,"scaleX":0.7,"scaleY":0.7,"blend":[770,1],"opacity":0,"color":[255,0,0],"action":[]},
  {"id":"Glow_01_18_0_0_0","type":"image","resPath":"effects/effectsRes/Glow_01.png",
     "ax":0.5,"ay":0.5,"x":-173,"y":58,"z":4,"scaleX":0.3,"scaleY":0.3,"blend":[770,1],"opacity":0,"color":[255,255,0],"action":[]},
 ],
"views5_delay19":[
  {"id":"Glow_01_4_0","type":"image","resPath":"effects/effectsRes/Glow_01.png",
     "ax":0.5,"ay":0.5,"x":-252,"y":399,"z":1,"scaleX":1.5,"scaleY":1.5,"blend":[770,1],"opacity":0,"color":[255,63,0],"action":[]},
 ],
"views5_delay20":[
  {"id":"person_Sprite_21_0_0","type":"image","resPath":"effects/effectsRes/Saint Seiya_attack_0_0000.png",
     "ax":0.5,"ay":0.5,"x":-260,"y":350,"z":0,"scaleX":1.0,"scaleY":1.0,"blend":[770,771],"action":[]},
 ],
 "views2_delay26":[
  {"id":"Glow_02_5","type":"image","resPath":"effects/effectsRes/Glow_02.png",
     "ax":0.5,"ay":0.5,"x":0,"y":0,"z":0,"scaleX":0.1,"scaleY":0.1,"blend":[1,1],"opacity":0,"color":[255,105,0],"action":[]},
  {"id":"Glow_02_5_0","type":"image","resPath":"effects/effectsRes/Glow_02.png",
     "ax":0.5,"ay":0.5,"x":0,"y":0,"z":1,"scaleX":0.1,"scaleY":0.1,"blend":[1,1],"opacity":0,"action":[]},
 ],
"views2_delay29":[
  {"id":"Strike_00000_4","type":"animate","frames":5,"time":0.200,"name":"Strike_0_Orange_","tab":{"beginNum":0,"plist":"effects/effectsRes/Strike_0_Orange.plist","isRepeat":false},
     "ax":0.2,"ay":0.5,"x":0,"y":0,"z":1,"scaleX":0.47,"scaleY":0.7,"blend":[1,1],"opacity":0,"action":[]},
  {"id":"Sprite_7","type":"animate","frames":4,"time":0.200,"name":"kaihuo_Yellow_","tab":{"beginNum":0,"plist":"effects/effectsRes/Fire.plist","isRepeat":false},
     "r":-90,"ax":0.5,"ay":0.8,"x":0,"y":2,"z":2,"scaleX":1.4,"scaleY":1,"blend":[1,1],"opacity":0,"action":[]},
 ],
"views2_delay33":[
  {"id":"Sprite_8","type":"animate","frames":6,"time":0.417,"name":"HuoQiu_","tab":{"beginNum":0,"plist":"effects/effectsRes/HuoQiu.plist","isRepeat":false},
     "r":90,"ax":0.4967,"ay":0.8786,"x":100,"y":0,"z":2,"scaleX":2.0,"scaleY":2.0,"blend":[1,771],"opacity":255,"color":[127,84,0],"action":[]},
  {"id":"Sprite_8_0","type":"animate","frames":6,"time":0.417,"name":"HuoQiu_","tab":{"beginNum":0,"plist":"effects/effectsRes/HuoQiu.plist","isRepeat":false},
     "r":90,"ax":0.4967,"ay":0.8786,"x":100,"y":0,"z":3,"scaleX":2.0,"scaleY":2.0,"blend":[1,1],"opacity":255,"action":[]},
 ],
"views2_delay55":[
  {"id":"RTD0_00_3","type":"animate","frames":8,"time":0.583,"name":"RTD_","tab":{"beginNum":0,"plist":"effects/effectsRes/RTD.plist","isRepeat":false},
     "ax":0.5,"ay":0.5,"x":0,"y":0,"z":1,"scaleX":1.0,"scaleY":1.0,"blend":[1,1],"opacity":0,"color":[255,137,0],"action":[]},
  {"id":"RTD0_00_3_0","type":"animate","frames":8,"time":0.583,"name":"RTD_","tab":{"beginNum":0,"plist":"effects/effectsRes/RTD.plist","isRepeat":false},
     "ax":0.5,"ay":0.5,"x":0,"y":0,"z":2,"scaleX":1.0,"scaleY":1.0,"blend":[1,1],"opacity":0,"color":[255,202,140],"action":[]},
 ],

 
"godSkill_views1_delay0":[
  {"id":"Common_00000_32","type":"animate","frames":12,"time":0.550,"name":"Common_0_","tab":{"beginNum":0,"plist":"effects/effectsRes/Common_0.plist","isRepeat":false},
     "ax":0.5,"ay":0.5,"x":747,"y":-524,"z":-3,"scaleX":3.3,"scaleY":3.3,"blend":[1,771],"opacity":0,"color":[255,0,0],"action":[]},
  {"id":"Common_00000_32_0","type":"animate","frames":12,"time":0.550,"name":"Common_0_","tab":{"beginNum":0,"plist":"effects/effectsRes/Common_0.plist","isRepeat":false},
     "ax":0.5,"ay":0.5,"x":747,"y":-524,"z":-2,"scaleX":3.3,"scaleY":3.3,"blend":[1,1],"opacity":0,"color":[255,0,0],"action":[]},
 ],
"godSkill_views1_delay15":[
  {"id":"Sprite_13","type":"animate","frames":6,"time":0.417,"name":"HuiXian_","tab":{"beginNum":0,"plist":"effects/effectsRes/HuiXian.plist","isRepeat":true},
     "ax":0.5,"ay":0.5,"x":-106,"y":-458,"z":-7,"scaleX":1.8067,"scaleY":1.4465,"blend":[1,771],"opacity":0,"color":[255,0,38],"action":[]},
 ],
"godSkill_views1_delay15_up":[
  {"id":"Buff_00000_14","type":"animate","frames":8,"time":0.583,"name":"Buff_","tab":{"beginNum":0,"plist":"effects/effectsRes/Buff.plist","isRepeat":true},
     "ax":0.5,"ay":0.3,"x":-5,"y":56,"z":0,"scaleX":1.9111,"scaleY":1.6702,"blend":[1,771],"opacity":0,"color":[255,0,0],"action":[]},
  {"id":"Particle_1","type":"particle","resPath":"particles/battleEffectPointUp.json",
     "x":5,"y":-34,"z":1,"scaleX":1.2959,"scaleY":1.3945,"blend":[1,1],"action":[]},
 ],
"godSkill_views1_delay20":[
  {"id":"Glow_01_23_0_0","type":"image","resPath":"partiPointBlue2.png",
     "ax":0.5,"ay":0.5,"x":751,"y":-537,"z":-1,"scaleX":4,"scaleY":4,"blend":[770,1],"opacity":0,"color":[255,0,0],"action":[]},
 ],
"godSkill_views1_delay55":[
  {"id":"Glow_16_2_0","type":"image","resPath":"partiPointBlue2.png",
     "ax":0.5,"ay":0.5,"x":-93,"y":-463,"z":-6,"scaleX":8.0,"scaleY":6,"blend":[1,771],"opacity":0,"color":[0,0,0],"action":[]},
  {"id":"Ground_00000_1","type":"animate","frames":12,"time":0.550,"name":"GroundGlow_","tab":{"beginNum":0,"plist":"effects/effectsRes/GroundGlow.plist","isRepeat":true},
     "ax":0.5,"ay":0.5,"x":-97,"y":-453,"z":-5,"scaleX":4,"scaleY":3,"blend":[1,771],"opacity":0,"color":[0,0,0],"action":[]},
  {"id":"Glow_16_2","type":"image","resPath":"partiPointBlue2.png",
     "ax":0.5,"ay":0.5,"x":-93,"y":-463,"z":-4,"scaleX":9.6,"scaleY":7.2,"blend":[770,1],"opacity":0,"color":[255,0,0],"action":[]},
 ],
"godSkill_views2_delay29":[
  {"id":"Fire_Ball_00000_2_move","type":"image","resPath":"effects/effectsRes/4015_Fire_Ball.png",
     "ax":0.5,"ay":0.5,"x":130,"y":-28,"z":-3,"scaleX":0.5,"scaleY":0.5,"blend":[1,771],"opacity":0,"color":[26,26,26],"action":[]},
  {"id":"Fire_Ball_00000_2_0_move","type":"image","resPath":"effects/effectsRes/4015_Fire_Ball.png",
     "ax":0.5,"ay":0.5,"x":130,"y":-28,"z":-2,"scaleX":0.5,"scaleY":0.5,"blend":[770,1],"opacity":0,"color":[0,0,0],"action":[]},
  {"id":"Glow_01_3_move","type":"image","resPath":"effects/effectsRes/Glow_01.png",
     "ax":0.5,"ay":0.5,"x":131,"y":-47,"z":-1,"scaleX":1.5,"scaleY":0.6522,"blend":[1,1],"opacity":0,"color":[0,0,0],"action":[]},
  {"id":"Fire_00000_4_move","type":"animate","frames":12,"time":0.550,"name":"4015_Fire_Blue_","tab":{"beginNum":0,"plist":"effects/effectsRes/Fire_Blue.plist","isRepeat":false},
     "r":-90,"ax":0.5,"ay":0.33,"x":60,"y":14,"z":0,"scaleX":1.98,"scaleY":3.09,"blend":[1,771],"opacity":0,"color":[255,0,0],"action":[]},
 ],
"godSkill_views3_delay63":[
  {"id":"Shockwave_1111","type":"animate","frames":12,"time":0.550,"name":"Shockwave_06_","tab":{"beginNum":0,"plist":"effects/effectsRes/Shockwave_06.plist","isRepeat":false},
     "ax":0.5,"ay":0.5,"x":434,"y":-246,"z":-4,"scaleX":2.33,"scaleY":2.33,"blend":[1,771],"opacity":0,"color":[255,0,0],"action":[]},
  {"id":"Shockwave_00000_1111","type":"animate","frames":12,"time":0.550,"name":"Shockwave_06_","tab":{"beginNum":0,"plist":"effects/effectsRes/Shockwave_06.plist","isRepeat":false},
     "ax":0.5,"ay":0.5,"x":434,"y":-246,"z":-3,"scaleX":2.33,"scaleY":2.33,"blend":[770,1],"opacity":0,"color":[255,0,0],"action":[]},
  {"id":"Sprite_9_1111","type":"animate","frames":4,"time":0.250,"name":"Impact_1_","tab":{"beginNum":0,"plist":"effects/effectsRes/Impact_1.plist","isRepeat":false},
     "ax":0.5,"ay":0.5,"x":430,"y":-248,"z":-2,"scaleX":1.0,"scaleY":1.0,"blend":[1,771],"opacity":0,"color":[0,0,0],"action":[]},
  {"id":"Glow_01_00_11_1111","type":"image","resPath":"effects/effectsRes/Glow_01.png",
     "ax":0.5,"ay":0.5,"x":432,"y":-245,"z":-1,"scaleX":0.7,"scaleY":0.7,"blend":[770,1],"opacity":0,"color":[0,0,0],"action":[]},
  {"id":"Glow_01_15_1111","type":"image","resPath":"effects/effectsRes/Glow_01.png",
     "ax":0.5,"ay":0.5,"x":431,"y":-237,"z":3,"scaleX":2.0,"scaleY":2.0,"blend":[770,1],"opacity":0,"color":[22,2,0],"action":[]},
 ],
"godSkill_views3_delay64":[
  {"id":"Change_Buff_1111","type":"animate","frames":12,"time":0.917,"name":"4015_Change_Buff_","tab":{"beginNum":0,"plist":"effects/effectsRes/Change_Buff.plist","isRepeat":false},
     "ax":0.5,"ay":0.5,"x":432,"y":-227,"z":-7,"scaleX":5.0,"scaleY":5.0,"blend":[1,771],"opacity":0,"action":[]},
 ],
"godSkill_views3_delay65":[
  {"id":"Glow_01_11_1111","type":"image","resPath":"effects/effectsRes/Glow_01.png",
     "ax":0.5,"ay":0.5,"x":432,"y":-245,"z":-5,"scaleX":0.5,"scaleY":0.5,"blend":[1,771],"opacity":0,"color":[9,6,0],"action":[]},
 ],
 "godSkill_views3_delay69":[
  {"id":"Fire_00000_12_fff","type":"animate","frames":15,"time":1.167,"name":"4015_Fire_Blue_","tab":{"beginNum":0,"plist":"effects/effectsRes/Fire_Blue.plist","isRepeat":true},
     "ax":0.5,"ay":0.33,"x":437,"y":-195,"z":0,"scaleX":2.5,"scaleY":2.5,"blend":[1,771],"opacity":0,"color":[0,0,0],"action":[]},
 ],
"godSkill_views3_delay189":[
  {"id":"Glow_01_1111","type":"image","resPath":"effects/effectsRes/Glow_01.png",
     "ax":0.5,"ay":0.5,"x":442,"y":-255,"z":-6,"scaleX":1.0,"scaleY":1.0,"blend":[1,771],"opacity":0,"color":[9,6,0],"action":[]},
  {"id":"Shockwave_00000_6_1_1111","type":"animate","frames":12,"time":0.550,"name":"Shockwave_06_","tab":{"beginNum":0,"plist":"effects/effectsRes/Shockwave_06.plist","isRepeat":false},
     "ax":0.5,"ay":0.5,"x":434,"y":-246,"z":0,"scaleX":3.3,"scaleY":3.3,"blend":[1,771],"opacity":0,"color":[255,0,0],"action":[]},
  {"id":"Shockwave_00000_6_0_0_1111","type":"animate","frames":12,"time":0.550,"name":"Shockwave_06_","tab":{"beginNum":0,"plist":"effects/effectsRes/Shockwave_06.plist","isRepeat":false},
     "ax":0.5,"ay":0.5,"x":434,"y":-246,"z":1,"scaleX":3.3,"scaleY":3.3,"blend":[770,1],"opacity":0,"color":[255,0,0],"action":[]},
  {"id":"Sprite_9_0_1111","type":"animate","frames":4,"time":0.250,"name":"Impact_1_","tab":{"beginNum":0,"plist":"effects/effectsRes/Impact_1.plist","isRepeat":false},
     "ax":0.5,"ay":0.5,"x":430,"y":-248,"z":2,"scaleX":1.0,"scaleY":1.0,"blend":[1,771],"opacity":0,"color":[0,0,0],"action":[]},
 ]
}